nurdalib/__init__.py
nurdalib/main.py
nurdalib/table_functions.py
nurdalib-0.1.0.dist-info/LICENSE.txt
nurdalib-0.1.0.dist-info/METADATA
nurdalib-0.1.0.dist-info/WHEEL
nurdalib-0.1.0.dist-info/top_level.txt
nurdalib-0.1.0.dist-info/RECORD
