Metadata-Version: 2.1
Name: nurdalib
Version: 0.1.0
Summary: Homework 1 library
Home-page: https://engineering.nyu.edu/
Author: Nurdaulet Kaldanov
Author-email: nk3194@nyu.edu
License: MIT
Classifier: Intended Audience :: Developers
Classifier: License :: OSI Approved :: MIT License
Classifier: Programming Language :: Python
Classifier: Programming Language :: Python :: 3
Classifier: Programming Language :: Python :: 3.6
Classifier: Programming Language :: Python :: 3.7
Classifier: Programming Language :: Python :: 3.8
Classifier: Programming Language :: Python :: 3.9
Classifier: Operating System :: OS Independent
License-File: LICENSE.txt
Requires-Dist: polygon-api-client (==0.2.11)
